jogoel/__init__.py
jogoel/check.py
jogoel/lang.py
jogoel/variables.py
jogoel-0.0.1.dist-info/LICENSE
jogoel-0.0.1.dist-info/METADATA
jogoel-0.0.1.dist-info/WHEEL
jogoel-0.0.1.dist-info/top_level.txt
jogoel-0.0.1.dist-info/RECORD
