Metadata-Version: 2.1
Name: jogoel
Version: 0.0.1
Summary: Jogja Gaul Language Encoding. Not a Programming Language
Author-email: c0del1ar <aryakrishna436@gmail.com>
Project-URL: Homepage, https://github.com/c0del1ar/jogoel-lang
Project-URL: Bug Tracker, https://github.com/c0del1ar/jogoel-lang/issues
Classifier: Programming Language :: Python :: 3
Classifier: License :: OSI Approved :: MIT License
Classifier: Operating System :: OS Independent
Requires-Python: >=3.7
License-File: LICENSE
